linuxdialer/__init__.py
linuxdialer/cli_runner.py
linuxdialer/vcard_parse.py
linuxdialer/buttons/__init__.py
linuxdialer/buttons/database_utils.py
linuxdialer/buttons/sipcall.py
linuxdialer/buttons/translate_to_email.py
linuxdialer/buttons/truecaller.py
linuxdialer/buttons/add_to_addressbook/__init__.py
linuxdialer/buttons/add_to_addressbook/vcard.py
linuxdialer/buttons/add_to_addressbook/test/__init__.py
linuxdialer/buttons/add_to_addressbook/test/test_create_vcard.py
linuxdialer/buttons/icons/ata.png
linuxdialer/buttons/icons/call.png
linuxdialer/buttons/icons/truecaller.png
linuxdialer/buttons/icons/tte.png
linuxdialer/buttons/test/__init__.py
linuxdialer/buttons/test/test_add_to_addressbook_qt.py
linuxdialer/buttons/test/test_databaseutils.py
linuxdialer/buttons/test/test_translate_to_email_qt.py
linuxdialer/buttons/test/test_truecaller_generate_url.py
linuxdialer/buttons/test/test_button_framework_qt/__init__.py
linuxdialer/buttons/test/test_button_framework_qt/hello_once.py
linuxdialer/buttons/test/test_button_framework_qt/hello_twice.py
linuxdialer/buttons/test/test_button_framework_qt/test_button_framework_qt.py
linuxdialer/resources/iso-country.json
linuxdialer/resources/linuxdialer.desktop
linuxdialer/resources/linuxdialer.png
linuxdialer-1.5.5.data/data/share/applications/linuxdialer.desktop
linuxdialer-1.5.5.data/data/share/icons/hicolor/128x128/apps/linuxdialer.png
linuxdialer-1.5.5.data/scripts/linuxdialer
linuxdialer-1.5.5.dist-info/METADATA
linuxdialer-1.5.5.dist-info/RECORD
linuxdialer-1.5.5.dist-info/WHEEL
linuxdialer-1.5.5.dist-info/top_level.txt
