Metadata-Version: 2.1
Name: linuxdialer
Version: 1.5.5
Summary: Applications for handling tel: uri and vCard files
Home-page: https://salsa.debian.org/sanjaypra555-guest/linux-dialer/
Author: Sanjay Prajapat
Author-email: sanjaypra555@gmail.com
License: UNKNOWN
Project-URL: Source, https://salsa.debian.org/sanjaypra555-guest/linux-dialer/
Keywords: linuxdialer
Platform: UNKNOWN
Classifier: License :: OSI Approved :: GNU General Public License v3 (GPLv3)
Classifier: Operating System :: POSIX :: Linux
Classifier: Programming Language :: Python :: 3
Classifier: Programming Language :: Python :: 3.3
Classifier: Programming Language :: Python :: 3.4
Classifier: Programming Language :: Python :: 3.5
Classifier: Programming Language :: Python :: 3.6
Requires-Dist: phonenumbers
Requires-Dist: pytz
Requires-Dist: vobject
